pypause/__init__.py
pypause/pause.py
pypause-1.0.1.post1.dist-info/METADATA
pypause-1.0.1.post1.dist-info/WHEEL
pypause-1.0.1.post1.dist-info/top_level.txt
pypause-1.0.1.post1.dist-info/RECORD
