Metadata-Version: 2.4
Name: pypause
Version: 1.0.1.post1
Summary: Remember pause >nul from Windows Batch programming? Now it's in Python! This works on ALL platforms! (Windows, MacOS, Linux)
Author-email: "Shirley.XML" <kanolade@outlook.com>
License: GPL-3.0
